README.md
setup.py
benchlog/__init__.py
benchlog.egg-info/PKG-INFO
benchlog.egg-info/SOURCES.txt
benchlog.egg-info/dependency_links.txt
benchlog.egg-info/requires.txt
benchlog.egg-info/top_level.txt