Metadata-Version: 2.1
Name: benchlog
Version: 0.2.0
Summary: Log CPU and Memory usage for a project overtime and send to server
Home-page: https://github.com/Keydex/BenchLog
Author: Anthony Pham
Author-email: benchlogpy@gmail.com
License: MIT
Platform: UNKNOWN
Classifier: Programming Language :: Python :: 3
Classifier: License :: OSI Approved :: MIT License
Classifier: Operating System :: OS Independent
